<?xml version="1.0" encoding="UTF-8"?>
<objects serializationModel="Studio.02.02.00">
	<object class="AudioFile" id="{4b53fb69-f9fe-4e26-83f7-76837ea66bf1}">
		<property name="assetPath">
			<value>wood_ - light_2.wav</value>
		</property>
		<property name="frequencyInKHz">
			<value>48</value>
		</property>
		<property name="channelCount">
			<value>2</value>
		</property>
		<property name="length">
			<value>0.26887499999999998</value>
		</property>
		<relationship name="masterAssetFolder">
			<destination>{824f24c9-8672-4456-8fa3-c11973ce741f}</destination>
		</relationship>
	</object>
</objects>
